tknlp/__init__.py
tknlp/analysis.py
tknlp/cli.py
tknlp/contribute/__init__.py
tknlp/contribute/cleaner.py
tknlp/contribute/constants.py
tknlp/contribute/mongo.py
tknlp/model.py
tknlp/runner.py
tknlp/runner_bk.py
tknlp/spacy/__init__.py
tknlp/spacy/asent.py
tknlp/spacy/asent_rule.py
tknlp/spacy/constant.py
tknlp/spacy/covid.py
tknlp/spacy/covid_rule.py
tknlp/spacy/depress.py
tknlp/spacy/utils.py
tknlp/torch.py
tknlp/typing_.py
tknlp/utils.py
tknlp-0.1.6.dist-info/WHEEL
tknlp-0.1.6.dist-info/METADATA
tknlp-0.1.6.dist-info/RECORD
